{
  "settings": {
    "index.refresh_interval": "30s"
  },
  "mappings": {
    "properties": {
        "@timestamp": {
            "type": "date"
        },
        "@version": {
            "type": "integer"
        },
        "features": {
            "type": "text",
            "analyzer":"english",
            "fields": {
                "keyword": {
                    "type": "keyword",
                    "ignore_above": 2048
                }
            }
        },
        "shippingWeight": {
            "type": "float"
        },
        "width": {
            "type": "keyword",
            "ignore_above": 256
        },
        "depth": {
            "type": "text",
            "fields": {
                "keyword": {
                    "type": "keyword",
                    "ignore_above": 256
                }
            }
        },
        "height": {
            "type": "keyword",
            "ignore_above": 256
        },
        "weight": {
            "type": "keyword",
            "ignore_above": 256
        },
        "color": {
            "type": "text",
            "fields": {
                "keyword": {
                    "type": "keyword",
                    "ignore_above": 128
                }
            }
        },
        "condition": {
            "type": "keyword"
        },
        "modelNumber": {
            "type": "keyword"
        },
        "longDescription": {
            "type": "text",
            "analyzer": "english",
            "fields": {
                "keyword": {
                    "type": "keyword",
                    "ignore_above": 2048
                }
            }
        },
        "description": {
            "type": "text",
            "analyzer": "english",
            "fields": {
                "keyword": {
                    "type": "keyword",
                    "ignore_above": 2048
                }
            }
        },
        "shortDescription": {
            "type": "text",
            "analyzer": "english",
            "fields": {
                "keyword": {
                    "type": "keyword",
                    "ignore_above": 2048
                }
            }
        },
        "longDescriptionHtml": {
            "type": "text",
            "analyzer": "english",
            "fields": {
                "keyword": {
                    "type": "keyword",
                    "ignore_above": 2048
                }
            }
        },
        "shortDescriptionHtml": {
            "type": "text",
            "analyzer": "english",
            "fields": {
                "keyword": {
                    "type": "keyword",
                    "ignore_above": 2048
                }
            }
        },
        "relatedProducts": {
            "type": "keyword",
            "ignore_above": 256
        },
        "accessories": {
            "type": "keyword"
        },
        "active": {
            "type": "boolean"
        },
        "bestBuyItemId": {
            "type": "keyword"
        },
        "bestSellingRank": {
            "type": "integer"
        },
        "categoryLeaf": {
            "type": "keyword"
        },
        "categoryPath": {
            "type": "keyword"
        },
        "categoryPathCount": {
            "type": "integer"
        },
        "categoryPathIds": {
            "type": "keyword"
        },
        "class": {
            "type": "text",
            "fields": {
                "keyword": {
                    "type": "keyword",
                    "ignore_above": 256
                }
            }
        },
        "classId": {
            "type": "keyword"
        },
        "customerReviewAverage": {
            "type": "float"
        },
        "customerReviewCount": {
            "type": "integer"
        },
        "department": {
            "type": "text",
            "fields": {
                "keyword": {
                    "type": "keyword",
                    "ignore_above": 256
                }
            }
        },
        "departmentId": {
            "type": "keyword"
        },
        "digital": {
            "type": "boolean"
        },
        "frequentlyPurchasedWith": {
            "type": "keyword"
        },
        "homeDelivery": {
            "type": "boolean"
        },
        "image": {
            "type": "keyword"
        },
        "inStoreAvailability": {
            "type": "boolean"
        },
        "inStorePickup": {
            "type": "boolean"
        },
        "manufacturer": {
            "type": "keyword"
        },
        "name": {
            "type": "text",
            "analyzer": "english",
            "fields": {
                "keyword": {
                    "type": "keyword",
                    "ignore_above": 256
                }                
            }
        },
        "onSale": {
            "type": "boolean"
        },
        "onlineAvailability": {
            "type": "boolean"
        },
        "productId": {
            "type": "keyword"
        },
        "quantityLimit": {
            "type": "integer"
        },
        "regularPrice": {
            "type": "float"
        },
        "releaseDate": {
            "type": "date"
        },
        "salePrice": {
            "type": "float" 
        },
        "salesRankLongTerm": {
            "type": "integer"
        },
        "salesRankMediumTerm": {
            "type": "integer"
        },
        "salesRankShortTerm": {
            "type": "integer"
        },
        "shippingCost": {
            "type": "float"
        },
        "sku": {
            "type": "keyword",
            "ignore_above": 256
        },
        "startDate": {
            "type": "date"
        },
        "subclass": {
            "type": "text",
            "fields": {
                "keyword": {
                    "type": "keyword",
                    "ignore_above": 256
                }
            }
        },
        "subclassId": {
            "type": "keyword"
        },
        "tags": {
            "type": "text",
            "fields": {
                "keyword": {
                    "type": "keyword",
                    "ignore_above": 256
                }
            }
        },
        "type": {
            "type": "keyword"
        },
        "url": {
            "type": "keyword"
        }
    }
}
}